yt_upload/__init__.py
yt_upload/channel.py
yt_upload/components/__init__.py
yt_upload/components/_YTDetailsComponent.py
yt_upload/components/_YTStudioComponent.py
yt_upload/components/_YTVisibilityComponent.py
yt_upload/constants/caption_certifications.py
yt_upload/constants/categories.py
yt_upload/constants/comment_moderations.py
yt_upload/constants/education_acamedic_systems.py
yt_upload/constants/education_types.py
yt_upload/constants/formats.py
yt_upload/constants/indexes.py
yt_upload/constants/languages.py
yt_upload/constants/licenses.py
yt_upload/constants/sort_by.py
yt_upload/constants/visibilities.py
yt_upload/exceptions.py
yt_upload/loggers/__init__.py
yt_upload/loggers/_logadapter.py
yt_upload/loggers/_setup_logging.py
yt_upload/loggers/logformatter.py
yt_upload/loggers/logging_config.json
yt_upload/models/__init__.py
yt_upload/models/cookies.py
yt_upload/models/video.py
yt_upload/pages/__init__.py
yt_upload/pages/_YTDetailsPage.py
yt_upload/pages/_YTPage.py
yt_upload/pages/_YTStudioPage.py
yt_upload/pages/_YTVisibilityPage.py
yt_upload/pages/times.py
yt_upload/states/__init__.py
yt_upload/states/_YTDetailsStateGroup.py
yt_upload/states/_YTStudioStateGroup.py
yt_upload/states/_YTVisibilityStateGroup.py
yt_upload/states/base.py
yt_upload/typing.py
yt_upload/utils.py
yt_upload-1.0.0.dist-info/LICENSE
yt_upload-1.0.0.dist-info/METADATA
yt_upload-1.0.0.dist-info/WHEEL
yt_upload-1.0.0.dist-info/RECORD
