Metadata-Version: 2.1
Name: yt-upload
Version: 1.0.0
Summary: 
Author: monotirg
Author-email: monotirg@gmail.com
Requires-Python: >=3.11,<4.0
Classifier: Programming Language :: Python :: 3
Classifier: Programming Language :: Python :: 3.11
Classifier: Programming Language :: Python :: 3.12
Requires-Dist: playwright (>=1.41.1,<2.0.0)
Requires-Dist: pydantic (>=2.6.0,<3.0.0)
Requires-Dist: pymediainfo (>=6.1.0,<7.0.0)
